pyhelper3/FileHelper.py
pyhelper3/JanusGraphHelper.py
pyhelper3/MQTTConnectHelper.py
pyhelper3/MysqlHelper.py
pyhelper3/RegexHelper.py
pyhelper3/RequestHelper.py
pyhelper3/TimeHelper.py
pyhelper3/YamlHelper.py
pyhelper3/__init__.py
pyhelper3-0.0.6.dist-info/LICENSE
pyhelper3-0.0.6.dist-info/METADATA
pyhelper3-0.0.6.dist-info/WHEEL
pyhelper3-0.0.6.dist-info/top_level.txt
pyhelper3-0.0.6.dist-info/RECORD
