Metadata-Version: 2.1
Name: pyhelper3
Version: 0.0.6
Summary: UNKNOWN
Home-page: http://gitee.com/shellvv/pyhelper3
Author: shellvv
Author-email: shellvv@yeah.com
License: UNKNOWN
Platform: UNKNOWN
Classifier: Programming Language :: Python :: 3
Classifier: License :: OSI Approved :: MIT License
Classifier: Operating System :: OS Independent
Requires-Dist: requests
Requires-Dist: bs4
Requires-Dist: pymysql
